eclipsoid/__init__.py
eclipsoid/bounds.py
eclipsoid/ellipsoid.py
eclipsoid/light_curve.py
eclipsoid/oblate_GUI.py
eclipsoid/plotting_utils.py
eclipsoid/solution.py
eclipsoid/utils.py
eclipsoid/visualization.py
eclipsoid/legacy/light_curve.py
eclipsoid/numpy_src/__init__.py
eclipsoid/numpy_src/bounds.py
eclipsoid/numpy_src/solution.py
eclipsoid/numpy_src/utils.py
eclipsoid-0.0.2.dist-info/LICENSE
eclipsoid-0.0.2.dist-info/METADATA
eclipsoid-0.0.2.dist-info/WHEEL
eclipsoid-0.0.2.dist-info/top_level.txt
eclipsoid-0.0.2.dist-info/RECORD
