Metadata-Version: 2.2
Name: eclipsoid
Version: 0.0.2
Summary: Transit models for oblate planets in Jax
Author-email: Shishir Dholakia <dholakia.shishir@gmail.com>, Shashank Dholakia <s.dholakia@uq.edu.au>
License: MIT License
Project-URL: repository, https://github.com/shishirdholakia/jax0planet/
Keywords: python,exoplanet,machine-learning,jax,autodiff,differentiable,transit,telescope
Classifier: Programming Language :: Python :: 3
Classifier: Operating System :: OS Independent
Requires-Python: >=3.9
License-File: LICENSE
Requires-Dist: scipy
Requires-Dist: numpy
Requires-Dist: jaxoplanet
Requires-Dist: zodiax>=0.4.1
Requires-Dist: jaxlib<=0.4.32
Provides-Extra: extras
Requires-Dist: matplotlib; extra == "extras"
Requires-Dist: jupyter; extra == "extras"
Requires-Dist: jupyterlab; extra == "extras"
Requires-Dist: tqdm; extra == "extras"
Requires-Dist: numpyro; extra == "extras"
Provides-Extra: dev
Requires-Dist: pytest; extra == "dev"
